README.md
setup.cfg
setup.py
./LICENSE
requirements/base.txt
requirements/test.txt
src/ncbi/cloudblast/v1alpha/__init__.py
src/ncbi/cloudblast/v1alpha/api_pb2.py
src/ncbi/cloudblast/v1alpha/api_pb2_grpc.py
src/ncbi/cloudblast/v1alpha/blast_request_pb2.py
src/ncbi/cloudblast/v1alpha/blast_request_pb2_grpc.py
src/ncbi_cloudblast_api/__init__.py
src/ncbi_cloudblast_api/_common.py
src/ncbi_cloudblast_api/api_client.py
src/ncbi_cloudblast_api/converters.py
src/ncbi_cloudblast_api/models.py
src/ncbi_cloudblast_api/result.py
src/ncbi_cloudblast_api/status.py
src/ncbi_cloudblast_api/utils.py
src/ncbi_cloudblast_api.egg-info/PKG-INFO
src/ncbi_cloudblast_api.egg-info/SOURCES.txt
src/ncbi_cloudblast_api.egg-info/dependency_links.txt
src/ncbi_cloudblast_api.egg-info/not-zip-safe
src/ncbi_cloudblast_api.egg-info/requires.txt
src/ncbi_cloudblast_api.egg-info/top_level.txt